aop/__init__.py
aop/api/__init__.py
aop/api/base.py
aop/api/biz/__init__.py
aop/api/biz/AlibabaAccountAgentCrossBasicParam.py
aop/api/biz/AlibabaAccountBasicParam.py
aop/api/biz/AlibabaAccountPeriodListBuyerViewParam.py
aop/api/biz/AlibabaAlipayUrlGetParam.py
aop/api/biz/AlibabaCategoryAttributeGetParam.py
aop/api/biz/AlibabaCreateOrderPreviewParam.py
aop/api/biz/AlibabaCreditPayUrlGetParam.py
aop/api/biz/AlibabaCrossBorderPayUrlGetParam.py
aop/api/biz/AlibabaLogisticsMyFreightTemplateListGetParam.py
aop/api/biz/AlibabaLogisticsOpQueryLogisticCompanyListParam.py
aop/api/biz/AlibabaOrderMemoAddParam.py
aop/api/biz/AlibabaSubAccountListParam.py
aop/api/biz/AlibabaTradeAddFeedbackParam.py
aop/api/biz/AlibabaTradeAddresscodeParseParam.py
aop/api/biz/AlibabaTradeCancelParam.py
aop/api/biz/AlibabaTradeCreateCrossOrderParam.py
aop/api/biz/AlibabaTradeCreateRefundParam.py
aop/api/biz/AlibabaTradeGetBuyerOrderListParam.py
aop/api/biz/AlibabaTradeGetBuyerViewParam.py
aop/api/biz/AlibabaTradeGetLogisticsInfosBuyerViewParam.py
aop/api/biz/AlibabaTradeGetLogisticsTraceInfoBuyerViewParam.py
aop/api/biz/AlibabaTradeGetRefundReasonListParam.py
aop/api/biz/AlibabaTradePayProtocolPayIsopenParam.py
aop/api/biz/AlibabaTradePayProtocolPayPreparePayParam.py
aop/api/biz/AlibabaTradePayWayQueryParam.py
aop/api/biz/AlibabaTradeReceiveAddressGetParam.py
aop/api/biz/AlibabaTradeRefundBuyerQueryOrderRefundListParam.py
aop/api/biz/AlibabaTradeRefundOpQueryBatchRefundByOrderIdAndStatusParam.py
aop/api/biz/AlibabaTradeRefundOpQueryOrderRefundOperationListParam.py
aop/api/biz/AlibabaTradeRefundReturnGoodsParam.py
aop/api/biz/AlibabaTradeUploadRefundVoucherParam.py
aop/api/biz/BigcustomerMailNoQueryParam.py
aop/api/biz/CategoryTranslationGetByIdParam.py
aop/api/biz/ConsignmentCoInventoryParam.py
aop/api/biz/ConsignmentCoStatusSyncParam.py
aop/api/biz/ConsignmentTallyCreateParam.py
aop/api/biz/LabelUrlReceiveParam.py
aop/api/biz/LogisticsOrderGetOutOrderIdParam.py
wnaop-0.2.0.dist-info/METADATA
wnaop-0.2.0.dist-info/WHEEL
wnaop-0.2.0.dist-info/RECORD
